eftoolkit/__init__.py
eftoolkit/utils.py
eftoolkit/gsheets/__init__.py
eftoolkit/gsheets/utils.py
eftoolkit/gsheets/core/__init__.py
eftoolkit/gsheets/core/spreadsheet.py
eftoolkit/gsheets/core/worksheet.py
eftoolkit/gsheets/runner/__init__.py
eftoolkit/gsheets/runner/dashboard_runner.py
eftoolkit/gsheets/runner/registry.py
eftoolkit/gsheets/runner/types/__init__.py
eftoolkit/gsheets/runner/types/cell_location.py
eftoolkit/gsheets/runner/types/cell_range.py
eftoolkit/gsheets/runner/types/hook_context.py
eftoolkit/gsheets/runner/types/worksheet_asset.py
eftoolkit/gsheets/runner/types/worksheet_definition.py
eftoolkit/gsheets/runner/types/worksheet_formatting.py
eftoolkit/gsheets/types/__init__.py
eftoolkit/gsheets/types/cell_location.py
eftoolkit/gsheets/types/cell_range.py
eftoolkit/s3/__init__.py
eftoolkit/s3/filesystem.py
eftoolkit/sql/__init__.py
eftoolkit/sql/duckdb.py
eftoolkit-2.6.1.dist-info/METADATA
eftoolkit-2.6.1.dist-info/WHEEL
eftoolkit-2.6.1.dist-info/licenses/LICENSE
eftoolkit-2.6.1.dist-info/RECORD
