Metadata-Version: 2.4
Name: eftoolkit
Version: 2.6.1
Summary: A streamlined Python toolkit for everyday programming tasks and utilities
Project-URL: Documentation, https://tidbitstatistics.com/eftoolkit/
Project-URL: Homepage, https://github.com/ethanfuerst/eftoolkit
Project-URL: Repository, https://github.com/ethanfuerst/eftoolkit
Project-URL: Issues, https://github.com/ethanfuerst/eftoolkit/issues
Author-email: Ethan Fuerst <ethanfuerst@gmail.com>
License-Expression: MIT
License-File: LICENSE
Keywords: data-engineering,duckdb,google-sheets,pandas,s3,toolkit
Classifier: Development Status :: 3 - Alpha
Classifier: License :: OSI Approved :: MIT License
Classifier: Operating System :: OS Independent
Classifier: Programming Language :: Python :: 3
Classifier: Programming Language :: Python :: 3.10
Classifier: Programming Language :: Python :: 3.11
Classifier: Programming Language :: Python :: 3.12
Classifier: Programming Language :: Python :: 3.13
Requires-Python: >=3.10
Requires-Dist: boto3>=1.34
Requires-Dist: duckdb>=1.0
Requires-Dist: gspread>=6.0
Requires-Dist: pandas>=2.0
Requires-Dist: pyarrow>=15.0
Provides-Extra: dev
Requires-Dist: boto3>=1.34; extra == 'dev'
Requires-Dist: commitizen>=4.0; extra == 'dev'
Requires-Dist: mkdocs-material>=9.5; extra == 'dev'
Requires-Dist: mkdocs>=1.6; extra == 'dev'
Requires-Dist: mkdocstrings[python]>=0.27; extra == 'dev'
Requires-Dist: moto[s3]>=4.0; extra == 'dev'
Requires-Dist: pre-commit>=4.0; extra == 'dev'
Requires-Dist: pytest-cov>=5.0; extra == 'dev'
Requires-Dist: pytest>=8.0; extra == 'dev'
Requires-Dist: python-dotenv>=1.0; extra == 'dev'
Requires-Dist: ruff>=0.8; extra == 'dev'
Provides-Extra: s3-only
Requires-Dist: boto3>=1.34; extra == 's3-only'
Requires-Dist: pandas>=2.0; extra == 's3-only'
Requires-Dist: pyarrow>=15.0; extra == 's3-only'
Provides-Extra: sql-only
Requires-Dist: duckdb>=1.0; extra == 'sql-only'
Requires-Dist: pandas>=2.0; extra == 'sql-only'
